pylspci/__init__.py
pylspci/pci_parser.py
pylspci/pci_scanner.py
pylspci/consoles/__init__.py
pylspci/consoles/console.py
pylspci/consoles/local_console.py
pylspci/consoles/remote_console.py
py_lspci-0.0.9.dist-info/LICENSE
py_lspci-0.0.9.dist-info/METADATA
py_lspci-0.0.9.dist-info/WHEEL
py_lspci-0.0.9.dist-info/top_level.txt
py_lspci-0.0.9.dist-info/RECORD
