Metadata-Version: 2.1
Name: py-lspci
Version: 0.0.9
Summary: Parser for lspci output on remote or local machines
Home-page: https://github.com/YADRO-KNS/py-lspci
Author: Sergey Parshin
Author-email: s.parshin@yadro.com
License: UNKNOWN
Platform: UNKNOWN
Classifier: Development Status :: 4 - Beta
Classifier: Programming Language :: Python :: 3.7
Classifier: Programming Language :: Python :: 3.8
Classifier: Programming Language :: Python :: 3.9
Classifier: License :: OSI Approved :: MIT License
Classifier: Operating System :: Unix
Requires-Python: >=3.7
License-File: LICENSE
Requires-Dist: Fabric (>=2.6.0)
